{
    "000000": {
        "dirs": ["ИТМО<программист>", "МГТУ<программист>"],
        "exams": { "ru": 100, "math": 100, "inf": 100}
    },
    "000001": {
        "dirs": ["ИТМО<программист>", "МГТУ<программист>"],
        "exams": { "ru": 64, "math": 57, "inf": 58}
    },
    "000002": {
        "dirs": ["ИТМО<программист>", "МГТУ<программист>"],
        "exams": { "ru": 90, "math": 75, "inf": 94}
    },
    "000003": {
        "dirs": ["МГТУ<программист>", "МГТУ<инженер>"],
        "exams": { "ru": 64, "math": 57, "inf": 90, "ph": 58}
    },
    "000004": {
        "dirs": ["МИФИ<физик>", "МГТУ<инженер>"],
        "exams": { "ru": 90, "math": 90, "ph": 90}
    },
    "000005": {
        "dirs": ["МГТУ<инженер>"],
        "exams": { "ru": 63, "math": 64, "ph": 38}
    },
    "000006": {
        "dirs": ["МИФИ<физик>"],
        "exams": { "ru": 100, "math": 100, "ph": 100}
    },
    "000007": {
        "dirs": ["МИФИ<физик>", "МГТУ<инженер>"],
        "exams": { "ru": 59, "math": 74, "ph": 53}
    },
    "000008": {
        "dirs": ["МИФИ<физик>", "МГТУ<инженер>"],
        "exams": { "ru": 57, "math": 95, "ph": 93}
    },
    "000009": {
        "dirs": ["МИФИ<физик>", "МГТУ<инженер>"],
        "exams": { "ru": 90, "math": 90, "ph": 90}
    },
    "000010": {
        "dirs": ["ВШЭ<экономист>", "РЭУ<экономист>"],
        "exams": { "ru": 90, "math": 90, "soc": 90}
    },
    "000011": {
        "dirs": ["РЭУ<экономист>"],
        "exams": { "ru": 92, "math": 73, "soc": 64}
    },
    "000012": {
        "dirs": ["ВШЭ<экономист>", "МГТУ<инженер>"],
        "exams": { "ru": 100, "math": 100, "soc": 100, "inf": 100}
    },
    "000013": {
        "dirs": ["РЭУ<экономист>"],
        "exams": { "ru": 63, "math": 50, "soc": 100}
    }
}